pipdate/__about__.py
pipdate/__init__.py
pipdate/cli.py
pipdate/main.py
pipdate/update.py
pipdatedd-0.3.3.dist-info/LICENSE
pipdatedd-0.3.3.dist-info/METADATA
pipdatedd-0.3.3.dist-info/WHEEL
pipdatedd-0.3.3.dist-info/entry_points.txt
pipdatedd-0.3.3.dist-info/top_level.txt
pipdatedd-0.3.3.dist-info/RECORD
