Metadata-Version: 2.1
Name: pipdatedd
Version: 0.3.3
Summary: pip update helpers
Home-page: https://github.com/nschloe/pipdate
Author: Nico Schlömer
Author-email: nico.schloemer@gmail.com
License: License :: OSI Approved :: MIT License
Platform: UNKNOWN
Classifier: Development Status :: 5 - Production/Stable
Classifier: License :: OSI Approved :: MIT License
Classifier: Operating System :: OS Independent
Classifier: Programming Language :: Python
Classifier: Programming Language :: Python :: 2
Classifier: Programming Language :: Python :: 3
Classifier: Topic :: Software Development
Classifier: Topic :: Software Development :: Version Control
Classifier: Topic :: System :: Software Distribution
Requires-Dist: appdirs
Requires-Dist: requests
